wtf/__init__.py
wtf/configs.py
wtf/main.py
wtf/command_output_loggers/__init__.py
wtf/command_output_loggers/base.py
wtf/command_output_loggers/pty_logger.py
wtf/command_output_loggers/script_cmd_logger.py
wtf/constants/__init__.py
wtf/constants/constants.py
wtf/constants/models.py
wtf/constants/prompt.txt
wtf/llms/__init__.py
wtf/llms/pipeline.py
wtf/shells/__init__.py
wtf/shells/base.py
wtf/shells/bash.py
wtf/shells/fish.py
wtf/shells/zsh.py
wtf_cli-0.1.2.dist-info/METADATA
wtf_cli-0.1.2.dist-info/WHEEL
wtf_cli-0.1.2.dist-info/entry_points.txt
wtf_cli-0.1.2.dist-info/licenses/LICENSE
wtf_cli-0.1.2.dist-info/RECORD
