Metadata-Version: 2.4
Name: wtf-cli
Version: 0.1.2
Summary: WTF is a command-line tool that leverages LLMs to correct and enhance previously executed terminal commands. 
Project-URL: Homepage, https://github.com/Asugawara/WhatTheFuck
Project-URL: Repository, https://github.com/Asugawara/WhatTheFuck
Author-email: Asugawara <asgasw@gmail.com>
License-File: LICENSE
Classifier: Intended Audience :: Developers
Classifier: License :: OSI Approved :: MIT License
Classifier: Programming Language :: Python
Classifier: Programming Language :: Python :: 3 :: Only
Classifier: Programming Language :: Python :: 3.10
Classifier: Programming Language :: Python :: 3.11
Classifier: Programming Language :: Python :: 3.12
Classifier: Programming Language :: Python :: 3.13
Requires-Python: >=3.10
Requires-Dist: anthropic-haystack>=1.2.1
Requires-Dist: google-vertex-haystack>=4.0.1
Requires-Dist: haystack-ai>=2.8.0
Requires-Dist: logzero>=1.7.0
Requires-Dist: pyte>=0.8.2
Requires-Dist: rich>=13.9.4
